ovos_phal_plugin_connectivity_events/__init__.py
ovos_phal_plugin_connectivity_events/version.py
ovos_phal_plugin_connectivity_events-0.1.3.dist-info/licenses/LICENSE
ovos_phal_plugin_connectivity_events-0.1.3.dist-info/METADATA
ovos_phal_plugin_connectivity_events-0.1.3.dist-info/WHEEL
ovos_phal_plugin_connectivity_events-0.1.3.dist-info/entry_points.txt
ovos_phal_plugin_connectivity_events-0.1.3.dist-info/top_level.txt
ovos_phal_plugin_connectivity_events-0.1.3.dist-info/zip-safe
ovos_phal_plugin_connectivity_events-0.1.3.dist-info/RECORD
